mylib_mnemos/__init__.py
mylib_mnemos/gensim_tuto.py
mylib_mnemos/pipeline.py
mylib_mnemos-0.1.0.dist-info/WHEEL
mylib_mnemos-0.1.0.dist-info/METADATA
mylib_mnemos-0.1.0.dist-info/RECORD
